setup.py
coloradd/__init__.py
coloradd.egg-info/PKG-INFO
coloradd.egg-info/SOURCES.txt
coloradd.egg-info/dependency_links.txt
coloradd.egg-info/not-zip-safe
coloradd.egg-info/top_level.txt