Metadata-Version: 1.0
Name: coloradd
Version: 0.271
Summary: This is the color increase command for the turtle drawing command.配合Python海龟画图命令使用的颜色增加模块。
Home-page: https://github.com/lixingqiu/coloradd
Author: lixingqiu
Author-email: 406273900@qq.com
License: MIT
Platform: UNKNOWN
